recommender/__init__.py
recommender/cli.py
recommender/core.py
recommender_rakshita_102303498-0.2.1.dist-info/METADATA
recommender_rakshita_102303498-0.2.1.dist-info/WHEEL
recommender_rakshita_102303498-0.2.1.dist-info/entry_points.txt
recommender_rakshita_102303498-0.2.1.dist-info/top_level.txt
recommender_rakshita_102303498-0.2.1.dist-info/RECORD
