Metadata-Version: 2.4
Name: Recommender-Rakshita-102303498
Version: 0.2.1
Summary: A simple content-based recommender system
Author: Rakshita Garg
License: MIT License
Classifier: License :: OSI Approved :: MIT License
Classifier: Programming Language :: Python :: 3
Requires-Python: >=3.8
Requires-Dist: pandas
Requires-Dist: scikit-learn
